Workbook

Sheet Assumptions
A1: BetweenPages — Financial Model
A2: Influencer Affiliate Platform · Global · GCP Infrastructure
A4: ASSUMPTIONS | B4: Year 1 | C4: Year 2 | D4: Year 3 | E4: Year 4 | F4: Year 5
A5: GROWTH & USERS
A6: Monthly Active Users (MAU) | B6: 2000 | C6: 15000 | D6: 80000 | E6: 300000 | F6: 800000
A7: MAU Growth Rate (YoY) | B7: 0 | C7: =(C6-B6)/B6 -> 6.5 | D7: =(D6-C6)/C6 -> 4.3333333 | E7: =(E6-D6)/D6 -> 2.75 | F7: =(F6-E6)/E6 -> 1.6666667
A8: Registration-to-MAU Ratio | B8: 0.4 | C8: 0.35 | D8: 0.3 | E8: 0.28 | F8: 0.25
A9: Registered Users (cumulative) | B9: =IF(B8=0,0,B6/B8) -> 5000 | C9: =IF(C8=0,0,C6/C8) -> 42857.143 | D9: =IF(D8=0,0,D6/D8) -> 266666.67 | E9: =IF(E8=0,0,E6/E8) -> 1071428.6 | F9: =IF(F8=0,0,F6/F8) -> 3200000
A11: INFLUENCER METRICS
A12: Active Influencers | B12: 10 | C12: 75 | D12: 400 | E12: 1500 | F12: 5000
A13: Avg Books per Influencer List | B13: 12 | C13: 15 | D13: 18 | E13: 20 | F13: 22
A14: Total Curated Books (unique) | B14: =B12*B13*0.6 -> 72 | C14: =C12*C13*0.6 -> 675 | D14: =D12*D13*0.6 -> 4320 | E14: =E12*E13*0.6 -> 18000 | F14: =F12*F13*0.6 -> 66000
A15: Avg Followers per Influencer | B15: 5000 | C15: 8000 | D15: 12000 | E15: 15000 | F15: 18000
A16: Click-Through Rate (CTR) | B16: 0.03 | C16: 0.035 | D16: 0.04 | E16: 0.042 | F16: 0.045
A17: Conversion Rate (Click to Purchase) | B17: 0.08 | C17: 0.09 | D17: 0.1 | E17: 0.11 | F17: 0.12
A19: REVENUE ASSUMPTIONS
A20: Avg Book Price (Global Blended, USD) | B20: 18 | C20: 18 | D20: 19 | E20: 19 | F20: 20
A21: Avg Affiliate Commission Rate | B21: 0.065 | C21: 0.07 | D21: 0.075 | E21: 0.08 | F21: 0.085
A22: Platform Cut of Influencer Commission | B22: 0.25 | C22: 0.25 | D22: 0.25 | E22: 0.25 | F22: 0.25
A23: Direct Publisher Link Premium (%) | B23: 0 | C23: 0 | D23: 0.04 | E23: 0.06 | F23: 0.08
A24: % Revenue from Direct Publisher (Yr3+) | B24: 0 | C24: 0 | D24: 0.1 | E24: 0.25 | F24: 0.4
A26: GCP INFRASTRUCTURE COSTS
A27: Cloud Run / GKE (monthly, USD) | B27: 150 | C27: 600 | D27: 2500 | E27: 8000 | F27: 18000
A28: Firestore (monthly) | B28: 25 | C28: 200 | D28: 1200 | E28: 5000 | F28: 15000
A29: Gemini API Cost per 1K Sessions | B29: 1.5 | C29: 1.2 | D29: 1 | E29: 0.85 | F29: 0.75
A30: Avg Chat Sessions per MAU per Month | B30: 4 | C30: 5 | D30: 6 | E30: 6 | F30: 7
A31: Cloud CDN & Networking (monthly) | B31: 20 | C31: 100 | D31: 500 | E31: 1500 | F31: 4000
A32: Cloud Storage & Monitoring (monthly) | B32: 15 | C32: 50 | D32: 200 | E32: 600 | F32: 1500
A33: Domain, SSL, DNS (monthly) | B33: 10 | C33: 10 | D33: 15 | E33: 15 | F33: 20
A35: TEAM & OPERATING EXPENSES
A36: Founding Team (# people, equity) | B36: 2 | C36: 2 | D36: 2 | E36: 2 | F36: 2
A37: Paid Engineers (FTE) | B37: 0 | C37: 1 | D37: 3 | E37: 6 | F37: 10
A38: Avg Engineer Salary (annual, USD) | B38: 0 | C38: 60000 | D38: 65000 | E38: 70000 | F38: 75000
A39: Content / Influencer Manager (FTE) | B39: 0 | C39: 0 | D39: 1 | E39: 2 | F39: 3
A40: Avg Content Manager Salary (annual) | B40: 0 | C40: 0 | D40: 45000 | E40: 48000 | F40: 50000
A41: Marketing Budget (annual, USD) | B41: 500 | C41: 5000 | D41: 30000 | E41: 100000 | F41: 250000
A42: Legal & Compliance (annual) | B42: 500 | C42: 2000 | D42: 10000 | E42: 25000 | F42: 50000
A43: Misc / Admin (annual) | B43: 200 | C43: 1000 | D43: 5000 | E43: 15000 | F43: 30000

Sheet Revenue
A1: Revenue Model
A3: REVENUE BREAKDOWN | B3: Year 1 | C3: Year 2 | D3: Year 3 | E3: Year 4 | F3: Year 5
A4: AFFILIATE REVENUE
A5: Total Influencer Reach (impressions/mo) | B5: =Assumptions!B12*Assumptions!B15 -> 50000 | C5: =Assumptions!C12*Assumptions!C15 -> 600000 | D5: =Assumptions!D12*Assumptions!D15 -> 4800000 | E5: =Assumptions!E12*Assumptions!E15 -> 22500000 | F5: =Assumptions!F12*Assumptions!F15 -> 90000000
A6: Affiliate Link Clicks (monthly) | B6: =B5*Assumptions!B16 -> 1500 | C6: =C5*Assumptions!C16 -> 21000 | D6: =D5*Assumptions!D16 -> 192000 | E6: =E5*Assumptions!E16 -> 945000 | F6: =F5*Assumptions!F16 -> 4050000
A7: Purchases (monthly) | B7: =B6*Assumptions!B17 -> 120 | C7: =C6*Assumptions!C17 -> 1890 | D7: =D6*Assumptions!D17 -> 19200 | E7: =E6*Assumptions!E17 -> 103950 | F7: =F6*Assumptions!F17 -> 486000
A8: Gross Merchandise Value (GMV, annual) | B8: =B7*Assumptions!B20*12 -> 25920 | C8: =C7*Assumptions!C20*12 -> 408240 | D8: =D7*Assumptions!D20*12 -> 4377600 | E8: =E7*Assumptions!E20*12 -> 23700600 | F8: =F7*Assumptions!F20*12 -> 116640000
A9: Total Affiliate Commissions Earned | B9: =B8*Assumptions!B21 -> 1684.8 | C9: =C8*Assumptions!C21 -> 28576.8 | D9: =D8*Assumptions!D21 -> 328320 | E9: =E8*Assumptions!E21 -> 1896048 | F9: =F8*Assumptions!F21 -> 9914400
A10: Platform Affiliate Revenue (our cut) | B10: =B9*Assumptions!B22*(1-Assumptions!B24) -> 421.2 | C10: =C9*Assumptions!C22*(1-Assumptions!C24) -> 7144.2 | D10: =D9*Assumptions!D22*(1-Assumptions!D24) -> 73872 | E10: =E9*Assumptions!E22*(1-Assumptions!E24) -> 355509 | F10: =F9*Assumptions!F22*(1-Assumptions!F24) -> 1487160
A12: DIRECT PUBLISHER REVENUE (Year 3+)
A13: GMV via Direct Publisher Links | B13: =B8*Assumptions!B24 -> 0 | C13: =C8*Assumptions!C24 -> 0 | D13: =D8*Assumptions!D24 -> 437760 | E13: =E8*Assumptions!E24 -> 5925150 | F13: =F8*Assumptions!F24 -> 46656000
A14: Publisher Commission (affiliate + premium) | B14: =Assumptions!B21+Assumptions!B23 -> 0.065 | C14: =Assumptions!C21+Assumptions!C23 -> 0.07 | D14: =Assumptions!D21+Assumptions!D23 -> 0.115 | E14: =Assumptions!E21+Assumptions!E23 -> 0.14 | F14: =Assumptions!F21+Assumptions!F23 -> 0.165
A15: Direct Publisher Revenue | B15: =B13*B14*Assumptions!B22 -> 0 | C15: =C13*C14*Assumptions!C22 -> 0 | D15: =D13*D14*Assumptions!D22 -> 12585.6 | E15: =E13*E14*Assumptions!E22 -> 207380.25 | F15: =F13*F14*Assumptions!F22 -> 1924560
A17: TOTAL REVENUE | B17: =B10+B15 -> 421.2 | C17: =C10+C15 -> 7144.2 | D17: =D10+D15 -> 86457.6 | E17: =E10+E15 -> 562889.25 | F17: =F10+F15 -> 3411720
A18: Revenue per MAU (annual) | B18: =IF(Assumptions!B6=0,0,B17/Assumptions!B6) -> 0.2106 | C18: =IF(Assumptions!C6=0,0,C17/Assumptions!C6) -> 0.47628 | D18: =IF(Assumptions!D6=0,0,D17/Assumptions!D6) -> 1.08072 | E18: =IF(Assumptions!E6=0,0,E17/Assumptions!E6) -> 1.8762975 | F18: =IF(Assumptions!F6=0,0,F17/Assumptions!F6) -> 4.26465

Sheet Costs
A1: Cost Model
A3: COST BREAKDOWN | B3: Year 1 | C3: Year 2 | D3: Year 3 | E3: Year 4 | F3: Year 5
A4: GCP INFRASTRUCTURE (Annual)
A5: Compute (Cloud Run / GKE) | B5: =Assumptions!B27*12 -> 1800 | C5: =Assumptions!C27*12 -> 7200 | D5: =Assumptions!D27*12 -> 30000 | E5: =Assumptions!E27*12 -> 96000 | F5: =Assumptions!F27*12 -> 216000
A6: Firestore Database | B6: =Assumptions!B28*12 -> 300 | C6: =Assumptions!C28*12 -> 2400 | D6: =Assumptions!D28*12 -> 14400 | E6: =Assumptions!E28*12 -> 60000 | F6: =Assumptions!F28*12 -> 180000
A7: Gemini AI API | B7: =Assumptions!B6*Assumptions!B30*12/1000*Assumptions!B29 -> 144 | C7: =Assumptions!C6*Assumptions!C30*12/1000*Assumptions!C29 -> 1080 | D7: =Assumptions!D6*Assumptions!D30*12/1000*Assumptions!D29 -> 5760 | E7: =Assumptions!E6*Assumptions!E30*12/1000*Assumptions!E29 -> 18360 | F7: =Assumptions!F6*Assumptions!F30*12/1000*Assumptions!F29 -> 50400
A8: CDN & Networking | B8: =Assumptions!B31*12 -> 240 | C8: =Assumptions!C31*12 -> 1200 | D8: =Assumptions!D31*12 -> 6000 | E8: =Assumptions!E31*12 -> 18000 | F8: =Assumptions!F31*12 -> 48000
A9: Storage & Monitoring | B9: =Assumptions!B32*12 -> 180 | C9: =Assumptions!C32*12 -> 600 | D9: =Assumptions!D32*12 -> 2400 | E9: =Assumptions!E32*12 -> 7200 | F9: =Assumptions!F32*12 -> 18000
A10: Domain / SSL / DNS | B10: =Assumptions!B33*12 -> 120 | C10: =Assumptions!C33*12 -> 120 | D10: =Assumptions!D33*12 -> 180 | E10: =Assumptions!E33*12 -> 180 | F10: =Assumptions!F33*12 -> 240
A11: Total GCP Infrastructure | B11: =SUM(B5:B10) -> 2784 | C11: =SUM(C5:C10) -> 12600 | D11: =SUM(D5:D10) -> 58740 | E11: =SUM(E5:E10) -> 199740 | F11: =SUM(F5:F10) -> 512640
A13: TEAM & PERSONNEL (Annual)
A14: Engineering Team | B14: =Assumptions!B37*Assumptions!B38 -> 0 | C14: =Assumptions!C37*Assumptions!C38 -> 60000 | D14: =Assumptions!D37*Assumptions!D38 -> 195000 | E14: =Assumptions!E37*Assumptions!E38 -> 420000 | F14: =Assumptions!F37*Assumptions!F38 -> 750000
A15: Content / Influencer Management | B15: =Assumptions!B39*Assumptions!B40 -> 0 | C15: =Assumptions!C39*Assumptions!C40 -> 0 | D15: =Assumptions!D39*Assumptions!D40 -> 45000 | E15: =Assumptions!E39*Assumptions!E40 -> 96000 | F15: =Assumptions!F39*Assumptions!F40 -> 150000
A16: Total Personnel | B16: =SUM(B14:B15) -> 0 | C16: =SUM(C14:C15) -> 60000 | D16: =SUM(D14:D15) -> 240000 | E16: =SUM(E14:E15) -> 516000 | F16: =SUM(F14:F15) -> 900000
A18: OTHER OPERATING EXPENSES (Annual)
A19: Marketing & Growth | B19: =Assumptions!B41 -> 500 | C19: =Assumptions!C41 -> 5000 | D19: =Assumptions!D41 -> 30000 | E19: =Assumptions!E41 -> 100000 | F19: =Assumptions!F41 -> 250000
A20: Legal & Compliance | B20: =Assumptions!B42 -> 500 | C20: =Assumptions!C42 -> 2000 | D20: =Assumptions!D42 -> 10000 | E20: =Assumptions!E42 -> 25000 | F20: =Assumptions!F42 -> 50000
A21: Miscellaneous / Admin | B21: =Assumptions!B43 -> 200 | C21: =Assumptions!C43 -> 1000 | D21: =Assumptions!D43 -> 5000 | E21: =Assumptions!E43 -> 15000 | F21: =Assumptions!F43 -> 30000
A22: Total Other OpEx | B22: =SUM(B19:B21) -> 1200 | C22: =SUM(C19:C21) -> 8000 | D22: =SUM(D19:D21) -> 45000 | E22: =SUM(E19:E21) -> 140000 | F22: =SUM(F19:F21) -> 330000
A24: TOTAL COSTS | B24: =B11+B16+B22 -> 3984 | C24: =C11+C16+C22 -> 80600 | D24: =D11+D16+D22 -> 343740 | E24: =E11+E16+E22 -> 855740 | F24: =F11+F16+F22 -> 1742640
A25: Cost per MAU (annual) | B25: =IF(Assumptions!B6=0,0,B24/Assumptions!B6) -> 1.992 | C25: =IF(Assumptions!C6=0,0,C24/Assumptions!C6) -> 5.3733333 | D25: =IF(Assumptions!D6=0,0,D24/Assumptions!D6) -> 4.29675 | E25: =IF(Assumptions!E6=0,0,E24/Assumptions!E6) -> 2.8524667 | F25: =IF(Assumptions!F6=0,0,F24/Assumptions!F6) -> 2.1783

Sheet P&L Summary
A1: Profit & Loss Summary
A3: P&L STATEMENT | B3: Year 1 | C3: Year 2 | D3: Year 3 | E3: Year 4 | F3: Year 5
A4: Affiliate Revenue | B4: =Revenue!B10 -> 421.2 | C4: =Revenue!C10 -> 7144.2 | D4: =Revenue!D10 -> 73872 | E4: =Revenue!E10 -> 355509 | F4: =Revenue!F10 -> 1487160
A5: Direct Publisher Revenue | B5: =Revenue!B15 -> 0 | C5: =Revenue!C15 -> 0 | D5: =Revenue!D15 -> 12585.6 | E5: =Revenue!E15 -> 207380.25 | F5: =Revenue!F15 -> 1924560
A6: Total Revenue | B6: =Revenue!B17 -> 421.2 | C6: =Revenue!C17 -> 7144.2 | D6: =Revenue!D17 -> 86457.6 | E6: =Revenue!E17 -> 562889.25 | F6: =Revenue!F17 -> 3411720
A8: COSTS
A9: GCP Infrastructure | B9: =Costs!B11 -> 2784 | C9: =Costs!C11 -> 12600 | D9: =Costs!D11 -> 58740 | E9: =Costs!E11 -> 199740 | F9: =Costs!F11 -> 512640
A10: Personnel | B10: =Costs!B16 -> 0 | C10: =Costs!C16 -> 60000 | D10: =Costs!D16 -> 240000 | E10: =Costs!E16 -> 516000 | F10: =Costs!F16 -> 900000
A11: Other Operating Expenses | B11: =Costs!B22 -> 1200 | C11: =Costs!C22 -> 8000 | D11: =Costs!D22 -> 45000 | E11: =Costs!E22 -> 140000 | F11: =Costs!F22 -> 330000
A12: Total Costs | B12: =Costs!B24 -> 3984 | C12: =Costs!C24 -> 80600 | D12: =Costs!D24 -> 343740 | E12: =Costs!E24 -> 855740 | F12: =Costs!F24 -> 1742640
A14: OPERATING PROFIT (EBITDA) | B14: =B6-B12 -> -3562.8 | C14: =C6-C12 -> -73455.8 | D14: =D6-D12 -> -257282.4 | E14: =E6-E12 -> -292850.75 | F14: =F6-F12 -> 1669080
A15: Operating Margin | B15: =IF(B6=0,0,B14/B6) -> -8.4586895 | C15: =IF(C6=0,0,C14/C6) -> -10.281879 | D15: =IF(D6=0,0,D14/D6) -> -2.9758217 | E15: =IF(E6=0,0,E14/E6) -> -0.52026353 | F15: =IF(F6=0,0,F14/F6) -> 0.48921951
A16: Cumulative Profit / (Loss) | B16: =B14 -> -3562.8 | C16: =B16+C14 -> -77018.6 | D16: =C16+D14 -> -334301 | E16: =D16+E14 -> -627151.75 | F16: =E16+F14 -> 1041928.2
A18: KEY METRICS
A19: Monthly Active Users | B19: =Assumptions!B6 -> 2000 | C19: =Assumptions!C6 -> 15000 | D19: =Assumptions!D6 -> 80000 | E19: =Assumptions!E6 -> 300000 | F19: =Assumptions!F6 -> 800000
A20: Active Influencers | B20: =Assumptions!B12 -> 10 | C20: =Assumptions!C12 -> 75 | D20: =Assumptions!D12 -> 400 | E20: =Assumptions!E12 -> 1500 | F20: =Assumptions!F12 -> 5000
A21: Revenue per MAU | B21: =Revenue!B18 -> 0.2106 | C21: =Revenue!C18 -> 0.47628 | D21: =Revenue!D18 -> 1.08072 | E21: =Revenue!E18 -> 1.8762975 | F21: =Revenue!F18 -> 4.26465
A22: Cost per MAU | B22: =Costs!B25 -> 1.992 | C22: =Costs!C25 -> 5.3733333 | D22: =Costs!D25 -> 4.29675 | E22: =Costs!E25 -> 2.8524667 | F22: =Costs!F25 -> 2.1783
A23: GCP Cost as % of Revenue | B23: =IF(Revenue!B17=0,0,Costs!B11/Revenue!B17) -> 6.6096866 | C23: =IF(Revenue!C17=0,0,Costs!C11/Revenue!C17) -> 1.7636684 | D23: =IF(Revenue!D17=0,0,Costs!D11/Revenue!D17) -> 0.67940817 | E23: =IF(Revenue!E17=0,0,Costs!E11/Revenue!E17) -> 0.35484778 | F23: =IF(Revenue!F17=0,0,Costs!F11/Revenue!F17) -> 0.15025852
A24: Breakeven Year | B24: =IF(B14>0,"Y1",IF(C14>0,"Y2",IF(D14>0,"Y3",IF(E14>0,"Y4",IF(F14>0,"Y5","Not Yet"))))) -> Y5

Sheet Scenarios
A1: Scenario Analysis
A2: Conservative=60% of base, Aggressive=150%
A4: CONSERVATIVE SCENARIO | B4: Year 1 | C4: Year 2 | D4: Year 3 | E4: Year 4 | F4: Year 5
A5: MAU (60% of Base) | B5: =Assumptions!B6*0.6 -> 1200 | C5: =Assumptions!C6*0.6 -> 9000 | D5: =Assumptions!D6*0.6 -> 48000 | E5: =Assumptions!E6*0.6 -> 180000 | F5: =Assumptions!F6*0.6 -> 480000
A6: Active Influencers (60%) | B6: =Assumptions!B12*0.6 -> 6 | C6: =Assumptions!C12*0.6 -> 45 | D6: =Assumptions!D12*0.6 -> 240 | E6: =Assumptions!E12*0.6 -> 900 | F6: =Assumptions!F12*0.6 -> 3000
A7: Estimated Revenue | B7: =Revenue!B17*0.36 -> 151.632 | C7: =Revenue!C17*0.36 -> 2571.912 | D7: =Revenue!D17*0.36 -> 31124.736 | E7: =Revenue!E17*0.36 -> 202640.13 | F7: =Revenue!F17*0.36 -> 1228219.2
A8: Estimated Costs | B8: =Costs!B11*0.6+Costs!B16+Costs!B22*0.8 -> 2630.4 | C8: =Costs!C11*0.6+Costs!C16+Costs!C22*0.8 -> 73960 | D8: =Costs!D11*0.6+Costs!D16+Costs!D22*0.8 -> 311244 | E8: =Costs!E11*0.6+Costs!E16+Costs!E22*0.8 -> 747844 | F8: =Costs!F11*0.6+Costs!F16+Costs!F22*0.8 -> 1471584
A9: Operating Profit | B9: =B7-B8 -> -2478.768 | C9: =C7-C8 -> -71388.088 | D9: =D7-D8 -> -280119.26 | E9: =E7-E8 -> -545203.87 | F9: =F7-F8 -> -243364.8
A11: BASE CASE | B11: Year 1 | C11: Year 2 | D11: Year 3 | E11: Year 4 | F11: Year 5
A12: MAU | B12: =Assumptions!B6 -> 2000 | C12: =Assumptions!C6 -> 15000 | D12: =Assumptions!D6 -> 80000 | E12: =Assumptions!E6 -> 300000 | F12: =Assumptions!F6 -> 800000
A13: Active Influencers | B13: =Assumptions!B12 -> 10 | C13: =Assumptions!C12 -> 75 | D13: =Assumptions!D12 -> 400 | E13: =Assumptions!E12 -> 1500 | F13: =Assumptions!F12 -> 5000
A14: Total Revenue | B14: =Revenue!B17 -> 421.2 | C14: =Revenue!C17 -> 7144.2 | D14: =Revenue!D17 -> 86457.6 | E14: =Revenue!E17 -> 562889.25 | F14: =Revenue!F17 -> 3411720
A15: Total Costs | B15: =Costs!B24 -> 3984 | C15: =Costs!C24 -> 80600 | D15: =Costs!D24 -> 343740 | E15: =Costs!E24 -> 855740 | F15: =Costs!F24 -> 1742640
A16: Operating Profit | B16: =B14-B15 -> -3562.8 | C16: =C14-C15 -> -73455.8 | D16: =D14-D15 -> -257282.4 | E16: =E14-E15 -> -292850.75 | F16: =F14-F15 -> 1669080
A18: AGGRESSIVE SCENARIO | B18: Year 1 | C18: Year 2 | D18: Year 3 | E18: Year 4 | F18: Year 5
A19: MAU (150% of Base) | B19: =Assumptions!B6*1.5 -> 3000 | C19: =Assumptions!C6*1.5 -> 22500 | D19: =Assumptions!D6*1.5 -> 120000 | E19: =Assumptions!E6*1.5 -> 450000 | F19: =Assumptions!F6*1.5 -> 1200000
A20: Active Influencers (150%) | B20: =Assumptions!B12*1.5 -> 15 | C20: =Assumptions!C12*1.5 -> 112.5 | D20: =Assumptions!D12*1.5 -> 600 | E20: =Assumptions!E12*1.5 -> 2250 | F20: =Assumptions!F12*1.5 -> 7500
A21: Estimated Revenue | B21: =Revenue!B17*2.25 -> 947.7 | C21: =Revenue!C17*2.25 -> 16074.45 | D21: =Revenue!D17*2.25 -> 194529.6 | E21: =Revenue!E17*2.25 -> 1266500.8 | F21: =Revenue!F17*2.25 -> 7676370
A22: Estimated Costs | B22: =Costs!B11*1.5+Costs!B16*1.2+Costs!B22*1.3 -> 5736 | C22: =Costs!C11*1.5+Costs!C16*1.2+Costs!C22*1.3 -> 101300 | D22: =Costs!D11*1.5+Costs!D16*1.2+Costs!D22*1.3 -> 434610 | E22: =Costs!E11*1.5+Costs!E16*1.2+Costs!E22*1.3 -> 1100810 | F22: =Costs!F11*1.5+Costs!F16*1.2+Costs!F22*1.3 -> 2277960
A23: Operating Profit | B23: =B21-B22 -> -4788.3 | C23: =C21-C22 -> -85225.55 | D23: =D21-D22 -> -240080.4 | E23: =E21-E22 -> 165690.81 | F23: =F21-F22 -> 5398410
A25: SCENARIO COMPARISON — Operating Profit | B25: Year 1 | C25: Year 2 | D25: Year 3 | E25: Year 4 | F25: Year 5
A26: Conservative | B26: =B9 -> -2478.768 | C26: =C9 -> -71388.088 | D26: =D9 -> -280119.26 | E26: =E9 -> -545203.87 | F26: =F9 -> -243364.8
A27: Base Case | B27: =B16 -> -3562.8 | C27: =C16 -> -73455.8 | D27: =D16 -> -257282.4 | E27: =E16 -> -292850.75 | F27: =F16 -> 1669080
A28: Aggressive | B28: =B23 -> -4788.3 | C28: =C23 -> -85225.55 | D28: =D23 -> -240080.4 | E28: =E23 -> 165690.81 | F28: =F23 -> 5398410
